wellplate_image/__init__.py
wellplate_image/marker_utils.py
wellplate_image/plate_utils.py
wellplate_image-0.1.1.dist-info/LICENSE
wellplate_image-0.1.1.dist-info/METADATA
wellplate_image-0.1.1.dist-info/WHEEL
wellplate_image-0.1.1.dist-info/RECORD
